pyRBM/__init__.py
pyRBM/Build/Classes.py
pyRBM/Build/Locations.py
pyRBM/Build/ProcessDescriptionFiles.py
pyRBM/Build/RuleMatching.py
pyRBM/Build/RuleTemplates.py
pyRBM/Build/Rules.py
pyRBM/Build/Utils.py
pyRBM/Build/__init__.py
pyRBM/Core/Cache.py
pyRBM/Core/Model.py
pyRBM/Core/Plotting.py
pyRBM/Core/__init__.py
pyRBM/Simulation/Location.py
pyRBM/Simulation/Rule.py
pyRBM/Simulation/RuleChain.py
pyRBM/Simulation/Solvers.py
pyRBM/Simulation/State.py
pyRBM/Simulation/StaticSeries.py
pyRBM/Simulation/Trajectory.py
pyRBM/Simulation/__init__.py
pyrbm-0.0.3.dist-info/METADATA
pyrbm-0.0.3.dist-info/WHEEL
pyrbm-0.0.3.dist-info/licenses/LICENSE
pyrbm-0.0.3.dist-info/RECORD
