Metadata-Version: 2.3
Name: pyRBM
Version: 0.0.3
Summary: A Python framework to build and simulate stochastic rules-based models
Project-URL: Homepage, https://github.com/Jamesflynn1/pyRBM/
Project-URL: Documentation, https://pyrbm.readthedocs.io/en/latest/index.html
Project-URL: Repository, https://github.com/Jamesflynn1/pyRBM/
Project-URL: Issues, https://github.com/Jamesflynn1/pyRBM/issues
Project-URL: Changelog, https://github.com/Jamesflynn1/pyRBM/releases
Author-email: James Flynn <jameswflynn@hotmail.co.uk>
License: GNU General Public License v3 (GPLv3)
License-File: LICENSE
Keywords: Gillespie Algorithm,Mathematical Modelling,Rules Based,SSA,Spatial Modelling,Stochastic Modelling,SymPy
Classifier: Development Status :: 2 - Pre-Alpha
Classifier: Intended Audience :: Developers
Classifier: Intended Audience :: Science/Research
Classifier: License :: OSI Approved :: MIT License
Classifier: Operating System :: OS Independent
Classifier: Programming Language :: Python :: 3
Classifier: Topic :: Scientific/Engineering :: Mathematics
Requires-Python: >=3.4
